<annotation>
	<folder>images</folder>
	<filename>73.jpg_resized.jpg</filename>
	<path>C:\Users\lab\Desktop\MuratEren\obj\v3\images_640\images\73.jpg_resized.jpg</path>
	<source>
		<database>Unknown</database>
	</source>
	<size>
		<width>640</width>
		<height>640</height>
		<depth>3</depth>
	</size>
	<segmented>0</segmented>
	<object>
		<name>APO</name>
		<pose>Unspecified</pose>
		<truncated>0</truncated>
		<difficult>0</difficult>
		<bndbox>
			<xmin>201</xmin>
			<ymin>207</ymin>
			<xmax>345</xmax>
			<ymax>425</ymax>
		</bndbox>
	</object>
</annotation>
