<annotation>
	<folder>images</folder>
	<filename>s_15409.jpg</filename>
	<path>C:\Users\lab\Desktop\MuratEren\obj\v3\images_640\images\s_15409.jpg</path>
	<source>
		<database>Unknown</database>
	</source>
	<size>
		<width>640</width>
		<height>640</height>
		<depth>3</depth>
	</size>
	<segmented>0</segmented>
	<object>
		<name>YPJ</name>
		<pose>Unspecified</pose>
		<truncated>0</truncated>
		<difficult>0</difficult>
		<bndbox>
			<xmin>77</xmin>
			<ymin>118</ymin>
			<xmax>271</xmax>
			<ymax>308</ymax>
		</bndbox>
	</object>
	<object>
		<name>YPG</name>
		<pose>Unspecified</pose>
		<truncated>0</truncated>
		<difficult>0</difficult>
		<bndbox>
			<xmin>353</xmin>
			<ymin>333</ymin>
			<xmax>575</xmax>
			<ymax>522</ymax>
		</bndbox>
	</object>
</annotation>
